{
  "_id": "SRi1lZrKCMweq1L4",
  "_key": "!actors!SRi1lZrKCMweq1L4",
  "folder": "1QPcErIwVgACFlzi",
  "name": "Archmage",
  "type": "npc",
  "img": "icons/svg/mystery-man.svg",
  "system": {
    "abilities": {
      "str": {
        "value": 10,
        "proficient": 0
      },
      "dex": {
        "value": 14,
        "proficient": 0
      },
      "con": {
        "value": 12,
        "proficient": 0
      },
      "int": {
        "value": 20,
        "proficient": 1
      },
      "wis": {
        "value": 15,
        "proficient": 1
      },
      "cha": {
        "value": 16,
        "proficient": 0
      }
    },
    "attributes": {
      "ac": {
        "calc": "flat",
        "flat": 17,
        "formula": ""
      },
      "hp": {
        "value": 170,
        "max": 170,
        "formula": "31d8 + 31",
        "temp": null,
        "tempmax": null
      },
      "movement": {
        "units": "ft",
        "hover": false,
        "walk": 30
      },
      "senses": {
        "units": "ft"
      },
      "init": {
        "ability": "dex",
        "bonus": ""
      }
    },
    "details": {
      "type": {
        "value": "humanoid",
        "subtype": "Wizar d",
        "swarm": "",
        "custom": ""
      },
      "alignment": "Neutro",
      "cr": 12,
      "xp": {
        "value": 8
      },
      "source": {
        "custom": "Monster Manual 2024"
      },
      "biography": {
        "value": ""
      }
    },
    "traits": {
      "size": "med",
      "di": {
        "value": [
          "psychic"
        ],
        "custom": ""
      },
      "dr": {
        "value": [],
        "custom": ""
      },
      "dv": {
        "value": [],
        "custom": ""
      },
      "ci": {
        "value": [],
        "custom": "Charmed (with Mind Blank)"
      },
      "languages": {
        "value": [],
        "custom": "Common plus five other languages"
      }
    },
    "skills": {
      "arc": {
        "value": 2,
        "ability": "int"
      },
      "his": {
        "value": 1,
        "ability": "int"
      },
      "prc": {
        "value": 1,
        "ability": "wis"
      }
    }
  },
  "prototypeToken": {
    "name": "Archmage",
    "actorLink": false,
    "sight": {
      "enabled": true
    },
    "texture": {
      "src": "modules/mm2024-pt-br/assets/tokens/archmage.webp"
    },
    "disposition": -1
  },
  "items": [
    {
      "_id": "oMCAYIksbZSCq0QK",
      "name": "Magic Resistance",
      "type": "feat",
      "img": "icons/svg/aura.svg",
      "system": {
        "description": {
          "value": "<p>The archmage has Advantage on sav- ing throws against spells and ot her magical effects.</p>",
          "chat": ""
        },
        "activation": {
          "type": "",
          "value": null
        },
        "uses": {
          "spent": 0,
          "max": "",
          "recovery": []
        },
        "type": {
          "value": "monster",
          "subtype": ""
        },
        "activities": {}
      },
      "flags": {
        "mm2024": {
          "mechanics": {},
          "source": "MM2024"
        }
      },
      "_key": "!actors.items!SRi1lZrKCMweq1L4.oMCAYIksbZSCq0QK"
    },
    {
      "_id": "xRwto0VR37WAnErR",
      "name": "Ataque Múltiplo",
      "type": "feat",
      "img": "icons/svg/aura.svg",
      "system": {
        "description": {
          "value": "<p>The archmage makes four Arcane Burst attacks.</p>",
          "chat": ""
        },
        "activation": {
          "type": "action",
          "value": null,
          "condition": ""
        },
        "uses": {
          "spent": 0,
          "max": "",
          "recovery": []
        },
        "type": {
          "value": "monster",
          "subtype": ""
        },
        "activities": {}
      },
      "flags": {
        "mm2024": {
          "mechanics": {},
          "source": "MM2024"
        }
      },
      "_key": "!actors.items!SRi1lZrKCMweq1L4.xRwto0VR37WAnErR"
    },
    {
      "_id": "Qg0zZfGVJxVKKSal",
      "name": "Arcane Burst",
      "type": "feat",
      "img": "icons/svg/aura.svg",
      "system": {
        "description": {
          "value": "<p>Rolagem de Ataque Corpo a Corpo ou à Distância: +9, alcance 5 ft . or range 150 ft. Acerto: 27 (4d1 0 + 5) Energia de dano.</p>",
          "chat": ""
        },
        "activation": {
          "type": "action",
          "value": null,
          "condition": ""
        },
        "uses": {
          "spent": 0,
          "max": "",
          "recovery": []
        },
        "type": {
          "value": "monster",
          "subtype": ""
        },
        "activities": {
          "h9dtAKnHr2wlKjXp": {
            "_id": "h9dtAKnHr2wlKjXp",
            "type": "attack",
            "activation": {
              "type": "action",
              "value": null,
              "override": true,
              "condition": ""
            },
            "attack": {
              "ability": "",
              "bonus": "9",
              "flat": true,
              "type": {
                "value": "ranged",
                "classification": "weapon"
              }
            },
            "damage": {
              "includeBase": false,
              "parts": [
                {
                  "number": 4,
                  "denomination": 10,
                  "bonus": "5",
                  "types": [
                    "force"
                  ],
                  "custom": {
                    "enabled": false,
                    "formula": ""
                  },
                  "scaling": {
                    "mode": "",
                    "number": 1,
                    "formula": ""
                  }
                }
              ]
            }
          }
        }
      },
      "flags": {
        "mm2024": {
          "mechanics": {
            "toHit": 9,
            "attackType": "ranged",
            "damageFormula": "4d10+5",
            "damageType": "force"
          },
          "source": "MM2024"
        }
      },
      "_key": "!actors.items!SRi1lZrKCMweq1L4.Qg0zZfGVJxVKKSal"
    },
    {
      "_id": "sebkU3wSUa4KA5m0",
      "name": "Misty Step (3/Day)",
      "type": "feat",
      "img": "icons/svg/aura.svg",
      "system": {
        "description": {
          "value": "<p>The mage casts Misty Step, using the same spellcasting ability as Conjuração.</p>",
          "chat": ""
        },
        "activation": {
          "type": "bonus",
          "value": null,
          "condition": ""
        },
        "uses": {
          "spent": 0,
          "max": "3",
          "recovery": [
            {
              "period": "day",
              "type": "recoverAll"
            }
          ]
        },
        "type": {
          "value": "monster",
          "subtype": ""
        },
        "activities": {}
      },
      "flags": {
        "mm2024": {
          "mechanics": {},
          "source": "MM2024"
        }
      },
      "_key": "!actors.items!SRi1lZrKCMweq1L4.sebkU3wSUa4KA5m0"
    },
    {
      "_id": "fzwfoiZcoGIAJBzx",
      "name": "Protective Magic (3/Day)",
      "type": "feat",
      "img": "icons/svg/aura.svg",
      "system": {
        "description": {
          "value": "<p>The archmage casts Counter- spell or Shield in response to the spell's trigger, using _ the same spellcasting ability as Conjuração. MAGES 1 99 MA G MIN Reckless Elemental Arsonist</p>",
          "chat": ""
        },
        "activation": {
          "type": "reaction",
          "value": null,
          "condition": ""
        },
        "uses": {
          "spent": 0,
          "max": "3",
          "recovery": [
            {
              "period": "day",
              "type": "recoverAll"
            }
          ]
        },
        "type": {
          "value": "monster",
          "subtype": ""
        },
        "activities": {}
      },
      "flags": {
        "mm2024": {
          "mechanics": {},
          "source": "MM2024"
        }
      },
      "_key": "!actors.items!SRi1lZrKCMweq1L4.fzwfoiZcoGIAJBzx"
    },
    {
      "_id": "t0ZWPFwJfBf20wlv",
      "name": "Conjuração",
      "type": "feat",
      "img": "icons/svg/aura.svg",
      "system": {
        "description": {
          "value": "<p>The archmage casts one of the following spells, using Inteligência as the spellcasting ability (spell save DC 17): À Vontade: Detect Magic, Detect Thoughts, Disguise Self, Invisibility , Light , Mage Armor (included in AC), Mage Hand, Prestidigitation 2/Dia Each: Fly, Elétrico Bolt (level 7 version) 1/Dia Each : Cone of Frio (level 9 version), Mind Blank (cast before com bat), Scrying, Teleport</p>",
          "chat": ""
        },
        "activation": {
          "type": "action",
          "value": null,
          "condition": ""
        },
        "uses": {
          "spent": 0,
          "max": "",
          "recovery": []
        },
        "type": {
          "value": "monster",
          "subtype": ""
        },
        "activities": {}
      },
      "flags": {
        "mm2024": {
          "mechanics": {},
          "source": "MM2024"
        }
      },
      "_key": "!actors.items!SRi1lZrKCMweq1L4.t0ZWPFwJfBf20wlv"
    }
  ],
  "flags": {
    "mm2024": {
      "nameEn": "Archmage",
      "page": 201,
      "cr": "12",
      "warnings": []
    }
  }
}