{
  "_id": "fXHKpoRI3zMzr6PR",
  "_key": "!actors!fXHKpoRI3zMzr6PR",
  "folder": "9eORFRgLi2o0urFB",
  "name": "Baboon",
  "type": "npc",
  "img": "modules/mm2024-pt-br/assets/portraits/baboon.webp",
  "system": {
    "abilities": {
      "str": {
        "value": 8,
        "proficient": 0
      },
      "dex": {
        "value": 14,
        "proficient": 0
      },
      "con": {
        "value": 77,
        "proficient": 0
      },
      "int": {
        "value": 4,
        "proficient": 0
      },
      "wis": {
        "value": 12,
        "proficient": 0
      },
      "cha": {
        "value": 6,
        "proficient": 0
      }
    },
    "attributes": {
      "ac": {
        "calc": "flat",
        "flat": 12,
        "formula": ""
      },
      "hp": {
        "value": 3,
        "max": 3,
        "formula": "7d6",
        "temp": null,
        "tempmax": null
      },
      "movement": {
        "units": "ft",
        "hover": false,
        "climb": 30
      },
      "senses": {
        "units": "ft"
      },
      "init": {
        "ability": "dex",
        "bonus": ""
      }
    },
    "details": {
      "type": {
        "value": "beast",
        "subtype": "",
        "swarm": "",
        "custom": ""
      },
      "alignment": "Sem Tendência",
      "cr": 0,
      "xp": {
        "value": 70
      },
      "source": {
        "custom": "Monster Manual 2024"
      },
      "biography": {
        "value": ""
      }
    },
    "traits": {
      "size": "sm",
      "di": {
        "value": [],
        "custom": ""
      },
      "dr": {
        "value": [],
        "custom": ""
      },
      "dv": {
        "value": [],
        "custom": ""
      },
      "ci": {
        "value": [],
        "custom": ""
      },
      "languages": {
        "value": [],
        "custom": "None"
      }
    },
    "skills": {}
  },
  "prototypeToken": {
    "name": "Baboon",
    "actorLink": false,
    "sight": {
      "enabled": true
    },
    "texture": {
      "src": "modules/mm2024-pt-br/assets/tokens/baboon.webp"
    },
    "disposition": -1
  },
  "items": [
    {
      "_id": "s4McTjQOplJC6A01",
      "name": "Pack Tactics",
      "type": "feat",
      "img": "icons/svg/aura.svg",
      "system": {
        "description": {
          "value": "<p>The baboon has Advantage on an attack roll against a creature if at least one of the baboon's allies is within 5 feet of the creature and the ally doesn't have the Incapacitado condition.</p>",
          "chat": ""
        },
        "activation": {
          "type": "",
          "value": null
        },
        "uses": {
          "spent": 0,
          "max": "",
          "recovery": []
        },
        "type": {
          "value": "monster",
          "subtype": ""
        },
        "activities": {}
      },
      "flags": {
        "mm2024": {
          "mechanics": {},
          "source": "MM2024"
        }
      },
      "_key": "!actors.items!fXHKpoRI3zMzr6PR.s4McTjQOplJC6A01"
    },
    {
      "_id": "8cDPG4YTMmf8dLUC",
      "name": "Habilidade",
      "type": "feat",
      "img": "icons/svg/aura.svg",
      "system": {
        "description": {
          "value": "<p>Q_ Bite. Rolagem de Ataque Corpo a Corpo: + l, alcance 5 ft. Acerto: l (1d4 - l) 0.. Perfurante de dano. BADGER T iny Beast, u·naligned AC 17 Iniciativa +0 (l 0) HP 5 (1d4 + 3) Sp eed 20 ft., Burrow 5 ft. MOD SAVE MOD SAVE MOD SAVE</p>",
          "chat": ""
        },
        "activation": {
          "type": "action",
          "value": null,
          "condition": ""
        },
        "uses": {
          "spent": 0,
          "max": "",
          "recovery": []
        },
        "type": {
          "value": "monster",
          "subtype": ""
        },
        "activities": {}
      },
      "flags": {
        "mm2024": {
          "mechanics": {},
          "source": "MM2024"
        }
      },
      "_key": "!actors.items!fXHKpoRI3zMzr6PR.8cDPG4YTMmf8dLUC"
    }
  ],
  "flags": {
    "mm2024": {
      "nameEn": "Baboon",
      "page": 351,
      "cr": "0",
      "warnings": []
    }
  }
}