{
  "_id": "atRrQdBVShFNEe0F",
  "_key": "!actors!atRrQdBVShFNEe0F",
  "folder": "9eORFRgLi2o0urFB",
  "name": "Gigante Wolf Spider",
  "type": "npc",
  "img": "modules/mm2024-pt-br/assets/portraits/giant-wolf-spider.webp",
  "system": {
    "abilities": {
      "str": {
        "value": 23,
        "proficient": 1
      },
      "dex": {
        "value": 14,
        "proficient": 1
      },
      "con": {
        "value": 12,
        "proficient": 0
      },
      "int": {
        "value": 5,
        "proficient": 0
      },
      "wis": {
        "value": 11,
        "proficient": 0
      },
      "cha": {
        "value": 4,
        "proficient": 0
      }
    },
    "attributes": {
      "ac": {
        "calc": "flat",
        "flat": 12,
        "formula": ""
      },
      "hp": {
        "value": 120,
        "max": 120,
        "formula": "16d12 + 1 6",
        "temp": null,
        "tempmax": null
      },
      "movement": {
        "units": "ft",
        "hover": false,
        "walk": 5,
        "swim": 80
      },
      "senses": {
        "units": "ft",
        "darkvision": 120
      },
      "init": {
        "ability": "dex",
        "bonus": ""
      }
    },
    "details": {
      "type": {
        "value": "beast",
        "subtype": "",
        "swarm": "",
        "custom": ""
      },
      "alignment": "Sem Tendência",
      "cr": 6,
      "xp": {
        "value": 2300
      },
      "source": {
        "custom": "Monster Manual 2024"
      },
      "biography": {
        "value": ""
      }
    },
    "traits": {
      "size": "huge",
      "di": {
        "value": [],
        "custom": ""
      },
      "dr": {
        "value": [],
        "custom": ""
      },
      "dv": {
        "value": [],
        "custom": ""
      },
      "ci": {
        "value": [],
        "custom": ""
      },
      "languages": {
        "value": [],
        "custom": ""
      }
    },
    "skills": {}
  },
  "prototypeToken": {
    "name": "Gigante Wolf Spider",
    "actorLink": false,
    "sight": {
      "enabled": true
    },
    "texture": {
      "src": "modules/mm2024-pt-br/assets/tokens/giant-wolf-spider.webp"
    },
    "disposition": -1
  },
  "items": [
    {
      "_id": "a6qCuvMvveGbkHuB",
      "name": "Ataque Múltiplo",
      "type": "feat",
      "img": "icons/svg/aura.svg",
      "system": {
        "description": {
          "value": "<p>The squid makes one Bite attack and one Tentacle attack.</p>",
          "chat": ""
        },
        "activation": {
          "type": "action",
          "value": null,
          "condition": ""
        },
        "uses": {
          "spent": 0,
          "max": "",
          "recovery": []
        },
        "type": {
          "value": "monster",
          "subtype": ""
        },
        "activities": {}
      },
      "flags": {
        "mm2024": {
          "mechanics": {},
          "source": "MM2024"
        }
      },
      "_key": "!actors.items!atRrQdBVShFNEe0F.a6qCuvMvveGbkHuB"
    },
    {
      "_id": "HakKRVrp8KKkZEv8",
      "name": "Bite",
      "type": "feat",
      "img": "icons/svg/aura.svg",
      "system": {
        "description": {
          "value": "<p>Rolagem de Ataque Corpo a Corpo: +9, alcance 5 ft. Acerto: 28 (4d1 0 + 6) Perfurante de dano.</p>",
          "chat": ""
        },
        "activation": {
          "type": "action",
          "value": null,
          "condition": ""
        },
        "uses": {
          "spent": 0,
          "max": "",
          "recovery": []
        },
        "type": {
          "value": "monster",
          "subtype": ""
        },
        "activities": {
          "MrwD9p5gekVZNgw4": {
            "_id": "MrwD9p5gekVZNgw4",
            "type": "attack",
            "activation": {
              "type": "action",
              "value": null,
              "override": true,
              "condition": ""
            },
            "attack": {
              "ability": "",
              "bonus": "9",
              "flat": true,
              "type": {
                "value": "melee",
                "classification": "weapon"
              }
            },
            "damage": {
              "includeBase": false,
              "parts": [
                {
                  "number": 4,
                  "denomination": 10,
                  "bonus": "6",
                  "types": [
                    "piercing"
                  ],
                  "custom": {
                    "enabled": false,
                    "formula": ""
                  },
                  "scaling": {
                    "mode": "",
                    "number": 1,
                    "formula": ""
                  }
                }
              ]
            }
          }
        }
      },
      "flags": {
        "mm2024": {
          "mechanics": {
            "toHit": 9,
            "attackType": "melee",
            "damageFormula": "4d10+6",
            "damageType": "piercing"
          },
          "source": "MM2024"
        }
      },
      "_key": "!actors.items!atRrQdBVShFNEe0F.HakKRVrp8KKkZEv8"
    },
    {
      "_id": "HXWelbWLbH0pV42h",
      "name": "Tentacle",
      "type": "feat",
      "img": "icons/svg/aura.svg",
      "system": {
        "description": {
          "value": "<p>Rolagem de Ataque Corpo a Corpo: +9, alcance 15 ft. Acerto: 19 (3d8 + 6) Concussão de dano. If o alvo is a Huge or smaller creature, it has the Agarrado condition (escape DC 16) from one of two tentacles, and the squid can pull o alvo up to 10 feet straight toward itself.</p>",
          "chat": ""
        },
        "activation": {
          "type": "action",
          "value": null,
          "condition": ""
        },
        "uses": {
          "spent": 0,
          "max": "",
          "recovery": []
        },
        "type": {
          "value": "monster",
          "subtype": ""
        },
        "activities": {
          "CeWF8TCBtdu7WKRS": {
            "_id": "CeWF8TCBtdu7WKRS",
            "type": "attack",
            "activation": {
              "type": "action",
              "value": null,
              "override": true,
              "condition": ""
            },
            "attack": {
              "ability": "",
              "bonus": "9",
              "flat": true,
              "type": {
                "value": "melee",
                "classification": "weapon"
              }
            },
            "damage": {
              "includeBase": false,
              "parts": [
                {
                  "number": 3,
                  "denomination": 8,
                  "bonus": "6",
                  "types": [
                    "bludgeoning"
                  ],
                  "custom": {
                    "enabled": false,
                    "formula": ""
                  },
                  "scaling": {
                    "mode": "",
                    "number": 1,
                    "formula": ""
                  }
                }
              ]
            }
          }
        }
      },
      "flags": {
        "mm2024": {
          "mechanics": {
            "toHit": 9,
            "attackType": "melee",
            "damageFormula": "3d8+6",
            "damageType": "bludgeoning"
          },
          "source": "MM2024"
        }
      },
      "_key": "!actors.items!atRrQdBVShFNEe0F.HXWelbWLbH0pV42h"
    },
    {
      "_id": "F1aeHNIq7mNt6tu1",
      "name": "Ink Cloud (1/Day)",
      "type": "feat",
      "img": "icons/svg/aura.svg",
      "system": {
        "description": {
          "value": "<p>Trigger: The squid takes de dano while underwater. Response: The squid releases ink that fills a 15-foot Cube centered on itself, and the squid moves up to its Swim Speed. The Cube is Heavily Ob- scured for l minute or until a strong current or similar effect disperses the ink. .APPENDIX A I ANIMALS GIANT WEASEL I I / BEWARE T H E FU RRE D G I AN T SNA KES O F THE YATI L</p>",
          "chat": ""
        },
        "activation": {
          "type": "reaction",
          "value": null,
          "condition": ""
        },
        "uses": {
          "spent": 0,
          "max": "1",
          "recovery": [
            {
              "period": "day",
              "type": "recoverAll"
            }
          ]
        },
        "type": {
          "value": "monster",
          "subtype": ""
        },
        "activities": {}
      },
      "flags": {
        "mm2024": {
          "mechanics": {},
          "source": "MM2024"
        }
      },
      "_key": "!actors.items!atRrQdBVShFNEe0F.F1aeHNIq7mNt6tu1"
    }
  ],
  "flags": {
    "mm2024": {
      "nameEn": "Giant Wolf Spider",
      "page": 362,
      "cr": "6",
      "warnings": []
    }
  }
}