{
  "_id": "LEjmVbfqRGZnsdU4",
  "_key": "!actors!LEjmVbfqRGZnsdU4",
  "folder": "mI6hZZeXOMovX9oy",
  "name": "Marid",
  "type": "npc",
  "img": "modules/mm2024-pt-br/assets/portraits/marid.webp",
  "system": {
    "abilities": {
      "str": {
        "value": 22,
        "proficient": 0
      },
      "dex": {
        "value": 12,
        "proficient": 1
      },
      "con": {
        "value": 26,
        "proficient": 0
      },
      "int": {
        "value": 18,
        "proficient": 0
      },
      "wis": {
        "value": 17,
        "proficient": 0
      },
      "cha": {
        "value": 18,
        "proficient": 1
      }
    },
    "attributes": {
      "ac": {
        "calc": "flat",
        "flat": 17,
        "formula": ""
      },
      "hp": {
        "value": 229,
        "max": 229,
        "formula": "17d10 + 136",
        "temp": null,
        "tempmax": null
      },
      "movement": {
        "units": "ft",
        "hover": false,
        "walk": 30,
        "fly": 60,
        "swim": 90
      },
      "senses": {
        "units": "ft",
        "darkvision": 120,
        "blindsight": 30
      },
      "init": {
        "ability": "dex",
        "bonus": ""
      }
    },
    "details": {
      "type": {
        "value": "elemental",
        "subtype": "genie",
        "swarm": "",
        "custom": ""
      },
      "alignment": "Caótico e Neutro",
      "cr": 11,
      "xp": {
        "value": 0
      },
      "source": {
        "custom": "Monster Manual 2024"
      },
      "biography": {
        "value": ""
      }
    },
    "traits": {
      "size": "lg",
      "di": {
        "value": [],
        "custom": ""
      },
      "dr": {
        "value": [
          "acid",
          "cold",
          "lightning"
        ],
        "custom": ""
      },
      "dv": {
        "value": [],
        "custom": ""
      },
      "ci": {
        "value": [],
        "custom": ""
      },
      "languages": {
        "value": [],
        "custom": "Primordial (Aquan)"
      }
    },
    "skills": {}
  },
  "prototypeToken": {
    "name": "Marid",
    "actorLink": false,
    "sight": {
      "enabled": true
    },
    "texture": {
      "src": "modules/mm2024-pt-br/assets/tokens/marid.webp"
    },
    "disposition": -1
  },
  "items": [
    {
      "_id": "TpqdGG6XBnISaMpi",
      "name": "Anfíbio",
      "type": "feat",
      "img": "icons/svg/aura.svg",
      "system": {
        "description": {
          "value": "<p>A criatura pode respirar ar e água.</p>",
          "chat": ""
        },
        "activation": {
          "type": "",
          "value": null
        },
        "uses": {
          "spent": 0,
          "max": "",
          "recovery": []
        },
        "type": {
          "value": "monster",
          "subtype": ""
        },
        "activities": {}
      },
      "flags": {
        "mm2024": {
          "mechanics": {},
          "source": "MM2024"
        }
      },
      "_key": "!actors.items!LEjmVbfqRGZnsdU4.TpqdGG6XBnISaMpi"
    },
    {
      "_id": "QSq8EfLuLUmMx213",
      "name": "Restauração Elemental",
      "type": "feat",
      "img": "icons/svg/aura.svg",
      "system": {
        "description": {
          "value": "<p>Se a criatura dies outside the Elemental Plane de Water, its body dissolves em brine, e it ganha um novo corpo em 1d4 dias, revivendo com todos os seus Pontos de Vida somewhere on the Plane de Water.</p>",
          "chat": ""
        },
        "activation": {
          "type": "",
          "value": null
        },
        "uses": {
          "spent": 0,
          "max": "",
          "recovery": []
        },
        "type": {
          "value": "monster",
          "subtype": ""
        },
        "activities": {}
      },
      "flags": {
        "mm2024": {
          "mechanics": {},
          "source": "MM2024"
        }
      },
      "_key": "!actors.items!LEjmVbfqRGZnsdU4.QSq8EfLuLUmMx213"
    },
    {
      "_id": "XfVzpyIuOXRaDgJf",
      "name": "Desejos",
      "type": "feat",
      "img": "icons/svg/aura.svg",
      "system": {
        "description": {
          "value": "<p>A criatura has a 30 percent chance de knowing the Wish spell. Se a criatura knows it, a criatura can cast it only on behalf de a non-genie creature who communicates a wish em a way a criatura can understand. Se a criatura casts the spell for the creature, a criatura suffers none de the spell's stress. Once a criatura has cast it three times, a criatura can't do so again for 365 dias.</p>",
          "chat": ""
        },
        "activation": {
          "type": "",
          "value": null
        },
        "uses": {
          "spent": 0,
          "max": "",
          "recovery": []
        },
        "type": {
          "value": "monster",
          "subtype": ""
        },
        "activities": {}
      },
      "flags": {
        "mm2024": {
          "mechanics": {},
          "source": "MM2024"
        }
      },
      "_key": "!actors.items!LEjmVbfqRGZnsdU4.XfVzpyIuOXRaDgJf"
    },
    {
      "_id": "dcNLlJoRTr71w25T",
      "name": "Ataque Múltiplo",
      "type": "feat",
      "img": "icons/svg/aura.svg",
      "system": {
        "description": {
          "value": "<p>A criatura makes three Aquatic Lash attacks.</p>",
          "chat": ""
        },
        "activation": {
          "type": "action",
          "value": null,
          "condition": ""
        },
        "uses": {
          "spent": 0,
          "max": "",
          "recovery": []
        },
        "type": {
          "value": "monster",
          "subtype": ""
        },
        "activities": {}
      },
      "flags": {
        "mm2024": {
          "mechanics": {},
          "source": "MM2024"
        }
      },
      "_key": "!actors.items!LEjmVbfqRGZnsdU4.dcNLlJoRTr71w25T"
    },
    {
      "_id": "Nm1nxOYsA33GPgHS",
      "name": "Aquatic Lash",
      "type": "feat",
      "img": "icons/svg/aura.svg",
      "system": {
        "description": {
          "value": "<p>Rolagem de Ataque Corpo a Corpo: +10, alcance 4,5 m. Acerto: 15 (2d8 + 6) dano cortante mais 9 (2d8) dano de frio.</p>",
          "chat": ""
        },
        "activation": {
          "type": "action",
          "value": null,
          "condition": ""
        },
        "uses": {
          "spent": 0,
          "max": "",
          "recovery": []
        },
        "type": {
          "value": "monster",
          "subtype": ""
        },
        "activities": {
          "CUpgmo5Dq0Vsf88D": {
            "_id": "CUpgmo5Dq0Vsf88D",
            "type": "attack",
            "activation": {
              "type": "action",
              "value": null,
              "override": true,
              "condition": ""
            },
            "attack": {
              "ability": "",
              "bonus": "10",
              "flat": true,
              "type": {
                "value": "melee",
                "classification": "weapon"
              }
            },
            "damage": {
              "includeBase": false,
              "parts": [
                {
                  "number": 2,
                  "denomination": 8,
                  "bonus": "6",
                  "types": [
                    "slashing"
                  ],
                  "custom": {
                    "enabled": false,
                    "formula": ""
                  },
                  "scaling": {
                    "mode": "",
                    "number": 1,
                    "formula": ""
                  }
                }
              ]
            }
          }
        }
      },
      "flags": {
        "mm2024": {
          "mechanics": {
            "toHit": 10,
            "attackType": "melee",
            "damageFormula": "2d8+6",
            "damageType": "slashing"
          },
          "source": "MM2024"
        }
      },
      "_key": "!actors.items!LEjmVbfqRGZnsdU4.Nm1nxOYsA33GPgHS"
    },
    {
      "_id": "bV75Ll277azLRhuo",
      "name": "Water Jet",
      "type": "feat",
      "img": "icons/svg/aura.svg",
      "system": {
        "description": {
          "value": "<p>Teste de Resistência de Destreza: CD 18, cada criatura em uma 18 m-long, 3 m-wide Linha. 31 (9d6) dano de frio. Se o alvo is a criatura Enorme ou menor, it é empurrado até 6 m para longe, em linha reta, de a criatura e fica com a condição Caído. Apenas metade do dano.</p>",
          "chat": ""
        },
        "activation": {
          "type": "action",
          "value": null,
          "condition": ""
        },
        "uses": {
          "spent": 0,
          "max": "",
          "recovery": []
        },
        "type": {
          "value": "monster",
          "subtype": ""
        },
        "activities": {
          "pfcBiB1zcZwpa3HX": {
            "_id": "pfcBiB1zcZwpa3HX",
            "type": "save",
            "activation": {
              "type": "action",
              "value": null,
              "override": true,
              "condition": ""
            },
            "save": {
              "ability": [
                "dex"
              ],
              "dc": {
                "calculation": "",
                "formula": "18"
              }
            },
            "damage": {
              "onSave": "half",
              "parts": []
            }
          }
        }
      },
      "flags": {
        "mm2024": {
          "mechanics": {
            "saveDc": 18,
            "saveAbility": "dex"
          },
          "source": "MM2024"
        }
      },
      "_key": "!actors.items!LEjmVbfqRGZnsdU4.bV75Ll277azLRhuo"
    },
    {
      "_id": "5Rv7eS1DlwF6NY0m",
      "name": "Conjuração",
      "type": "feat",
      "img": "icons/svg/aura.svg",
      "system": {
        "description": {
          "value": "<p>The marid casts one de the following spells, requiring no Material components e using Carisma as the spellcasting ability (spell save CD 16):</p>",
          "chat": ""
        },
        "activation": {
          "type": "action",
          "value": null,
          "condition": ""
        },
        "uses": {
          "spent": 0,
          "max": "",
          "recovery": []
        },
        "type": {
          "value": "monster",
          "subtype": ""
        },
        "activities": {}
      },
      "flags": {
        "mm2024": {
          "mechanics": {},
          "source": "MM2024"
        }
      },
      "_key": "!actors.items!LEjmVbfqRGZnsdU4.5Rv7eS1DlwF6NY0m"
    }
  ],
  "flags": {
    "mm2024": {
      "nameEn": "Marid",
      "page": 203,
      "cr": "11",
      "warnings": []
    }
  }
}