{
  "_id": "bZWvuXw4vdjnaxE2",
  "_key": "!actors!bZWvuXw4vdjnaxE2",
  "folder": "CVeezowVb7BNP8yc",
  "name": "Scarecrow",
  "type": "npc",
  "img": "modules/mm2024-pt-br/assets/portraits/scarecrow.webp",
  "system": {
    "abilities": {
      "str": {
        "value": 11,
        "proficient": 0
      },
      "dex": {
        "value": 13,
        "proficient": 0
      },
      "con": {
        "value": 1,
        "proficient": 0
      },
      "int": {
        "value": 10,
        "proficient": 0
      },
      "wis": {
        "value": 70,
        "proficient": 0
      },
      "cha": {
        "value": 13,
        "proficient": 0
      }
    },
    "attributes": {
      "ac": {
        "calc": "flat",
        "flat": 10,
        "formula": ""
      },
      "hp": {
        "value": 27,
        "max": 27,
        "formula": "6d8",
        "temp": null,
        "tempmax": null
      },
      "movement": {
        "units": "ft",
        "hover": false,
        "walk": 30
      },
      "senses": {
        "units": "ft",
        "darkvision": 60
      },
      "init": {
        "ability": "dex",
        "bonus": ""
      }
    },
    "details": {
      "type": {
        "value": "construct",
        "subtype": "",
        "swarm": "",
        "custom": ""
      },
      "alignment": "Caótico e Mau",
      "cr": 0,
      "xp": {
        "value": 200
      },
      "source": {
        "custom": "Monster Manual 2024"
      },
      "biography": {
        "value": ""
      }
    },
    "traits": {
      "size": "med",
      "di": {
        "value": [
          "poison"
        ],
        "custom": ""
      },
      "dr": {
        "value": [],
        "custom": ""
      },
      "dv": {
        "value": [],
        "custom": ""
      },
      "ci": {
        "value": [
          "charmed",
          "exhaustion",
          "frightened"
        ],
        "custom": ""
      },
      "languages": {
        "value": [],
        "custom": "Common plus one other language"
      }
    },
    "skills": {}
  },
  "prototypeToken": {
    "name": "Scarecrow",
    "actorLink": false,
    "sight": {
      "enabled": true
    },
    "texture": {
      "src": "modules/mm2024-pt-br/assets/tokens/scarecrow.webp"
    },
    "disposition": -1
  },
  "items": [
    {
      "_id": "qPD5pwD0VclFwZNs",
      "name": "Fearsome Claw",
      "type": "feat",
      "img": "icons/svg/aura.svg",
      "system": {
        "description": {
          "value": "<p>Rolagem de Ataque Corpo a Corpo: +3, alcance 5 ft. Acerto: 6 (2d4 + l) Cortante de dano, and o alvo has the Amedrontado condition until the end of the scarecrow's next turn.</p>",
          "chat": ""
        },
        "activation": {
          "type": "action",
          "value": null,
          "condition": ""
        },
        "uses": {
          "spent": 0,
          "max": "",
          "recovery": []
        },
        "type": {
          "value": "monster",
          "subtype": ""
        },
        "activities": {
          "LUHWKN0tNPyIP0AF": {
            "_id": "LUHWKN0tNPyIP0AF",
            "type": "attack",
            "activation": {
              "type": "action",
              "value": null,
              "override": true,
              "condition": ""
            },
            "attack": {
              "ability": "",
              "bonus": "3",
              "flat": true,
              "type": {
                "value": "melee",
                "classification": "weapon"
              }
            },
            "damage": {
              "includeBase": false,
              "parts": [
                {
                  "number": null,
                  "denomination": null,
                  "bonus": "",
                  "types": [
                    "slashing"
                  ],
                  "custom": {
                    "enabled": true,
                    "formula": "2d4+l"
                  },
                  "scaling": {
                    "mode": "",
                    "number": 1,
                    "formula": ""
                  }
                }
              ]
            }
          }
        }
      },
      "flags": {
        "mm2024": {
          "mechanics": {
            "toHit": 3,
            "attackType": "melee",
            "damageFormula": "2d4+l",
            "damageType": "slashing"
          },
          "source": "MM2024"
        }
      },
      "_key": "!actors.items!bZWvuXw4vdjnaxE2.qPD5pwD0VclFwZNs"
    },
    {
      "_id": "d3g7kIAvsktnNviH",
      "name": "Terrifying Glare",
      "type": "feat",
      "img": "icons/svg/aura.svg",
      "system": {
        "description": {
          "value": "<p>Sabedoria Teste de Resistência: DC l l, uma criatura the scarecrow can see within 30 feet. Falha: The target has the Amedrontado condition until the end of</p>",
          "chat": ""
        },
        "activation": {
          "type": "action",
          "value": null,
          "condition": ""
        },
        "uses": {
          "spent": 0,
          "max": "",
          "recovery": []
        },
        "type": {
          "value": "monster",
          "subtype": ""
        },
        "activities": {}
      },
      "flags": {
        "mm2024": {
          "mechanics": {},
          "source": "MM2024"
        }
      },
      "_key": "!actors.items!bZWvuXw4vdjnaxE2.d3g7kIAvsktnNviH"
    },
    {
      "_id": "K7Ajq0O73f4tAAhK",
      "name": "Y'",
      "type": "feat",
      "img": "icons/svg/aura.svg",
      "system": {
        "description": {
          "value": "<p>the scarecrow's next turn. While Amedrontado, o alvo Cl:'. <( has the Paralisado condition. SCOUT Medium or Small Humanoid, Neutral AC 13 Iniciativa +2 (12) HP 16(3d8+3) Speed 30 ft. M OD SAVE MOD SAVE M OD SA VE</p>",
          "chat": ""
        },
        "activation": {
          "type": "action",
          "value": null,
          "condition": ""
        },
        "uses": {
          "spent": 0,
          "max": "",
          "recovery": []
        },
        "type": {
          "value": "monster",
          "subtype": ""
        },
        "activities": {}
      },
      "flags": {
        "mm2024": {
          "mechanics": {},
          "source": "MM2024"
        }
      },
      "_key": "!actors.items!bZWvuXw4vdjnaxE2.K7Ajq0O73f4tAAhK"
    }
  ],
  "flags": {
    "mm2024": {
      "nameEn": "Scarecrow",
      "page": 271,
      "cr": "0",
      "warnings": []
    }
  }
}