{
  "_id": "VaMhGSEU1kCHtHFC",
  "_key": "!actors!VaMhGSEU1kCHtHFC",
  "folder": "lhndsA6Aflaa0nF6",
  "name": "Silver Dragon Wyrmling",
  "type": "npc",
  "img": "modules/mm2024-pt-br/assets/portraits/silver-dragon-wyrmling.webp",
  "system": {
    "abilities": {
      "str": {
        "value": 19,
        "proficient": 0
      },
      "dex": {
        "value": 10,
        "proficient": 1
      },
      "con": {
        "value": 17,
        "proficient": 0
      },
      "int": {
        "value": 12,
        "proficient": 0
      },
      "wis": {
        "value": 11,
        "proficient": 1
      },
      "cha": {
        "value": 15,
        "proficient": 0
      }
    },
    "attributes": {
      "ac": {
        "calc": "flat",
        "flat": 17,
        "formula": ""
      },
      "hp": {
        "value": 45,
        "max": 45,
        "formula": "6d8 + 18",
        "temp": null,
        "tempmax": null
      },
      "movement": {
        "units": "m",
        "hover": false,
        "walk": 9,
        "fly": 18
      },
      "senses": {
        "units": "m",
        "darkvision": 18,
        "blindsight": 3
      },
      "init": {
        "ability": "dex",
        "bonus": ""
      }
    },
    "details": {
      "type": {
        "value": "dragon",
        "subtype": "metallic",
        "swarm": "",
        "custom": ""
      },
      "alignment": "Leal e Bom",
      "cr": 2,
      "xp": {
        "value": 0
      },
      "source": {
        "custom": "Monster Manual 2024"
      },
      "biography": {
        "value": ""
      }
    },
    "traits": {
      "size": "med",
      "di": {
        "value": [
          "cold"
        ],
        "custom": ""
      },
      "dr": {
        "value": [],
        "custom": ""
      },
      "dv": {
        "value": [],
        "custom": ""
      },
      "ci": {
        "value": [],
        "custom": ""
      },
      "languages": {
        "value": [],
        "custom": "Dracônico"
      }
    },
    "skills": {
      "prc": {
        "value": 2,
        "ability": "wis"
      },
      "ste": {
        "value": 1,
        "ability": "dex"
      }
    }
  },
  "prototypeToken": {
    "name": "Silver Dragon Wyrmling",
    "actorLink": false,
    "sight": {
      "enabled": true
    },
    "texture": {
      "src": "modules/mm2024-pt-br/assets/tokens/silver-dragon-wyrmling.webp"
    },
    "disposition": -1
  },
  "items": [
    {
      "_id": "i3kABbIUvgeBiYSb",
      "name": "Ataque Múltiplo",
      "type": "feat",
      "img": "icons/svg/aura.svg",
      "system": {
        "description": {
          "value": "<p>A criatura faz dois ataques de Dilacerar.</p>",
          "chat": ""
        },
        "activation": {
          "type": "action",
          "value": null,
          "condition": ""
        },
        "uses": {
          "spent": 0,
          "max": "",
          "recovery": []
        },
        "type": {
          "value": "monster",
          "subtype": ""
        },
        "activities": {}
      },
      "flags": {
        "mm2024": {
          "mechanics": {},
          "source": "MM2024"
        }
      },
      "_key": "!actors.items!VaMhGSEU1kCHtHFC.i3kABbIUvgeBiYSb"
    },
    {
      "_id": "iV3DKLKD56K4Aq4T",
      "name": "Dilacerar",
      "type": "feat",
      "img": "icons/svg/aura.svg",
      "system": {
        "description": {
          "value": "<p>Ataque Corpo a Corpo: +6, alcance 1,5 m. 9 (1d10 + 4) de dano perfurante.</p>",
          "chat": ""
        },
        "activation": {
          "type": "action",
          "value": null,
          "condition": ""
        },
        "uses": {
          "spent": 0,
          "max": "",
          "recovery": []
        },
        "type": {
          "value": "monster",
          "subtype": ""
        },
        "activities": {
          "3XQ8z5keeJUxZvb9": {
            "_id": "3XQ8z5keeJUxZvb9",
            "type": "attack",
            "activation": {
              "type": "action",
              "value": null,
              "override": true,
              "condition": ""
            },
            "attack": {
              "ability": "",
              "bonus": "6",
              "flat": true,
              "type": {
                "value": "melee",
                "classification": "weapon"
              }
            },
            "damage": {
              "includeBase": false,
              "parts": [
                {
                  "number": 1,
                  "denomination": 10,
                  "bonus": "4",
                  "types": [
                    "piercing"
                  ],
                  "custom": {
                    "enabled": false,
                    "formula": ""
                  },
                  "scaling": {
                    "mode": "",
                    "number": 1,
                    "formula": ""
                  }
                }
              ]
            }
          }
        }
      },
      "flags": {
        "mm2024": {
          "mechanics": {
            "toHit": 6,
            "attackType": "melee",
            "damageFormula": "1d10+4",
            "damageType": "piercing"
          },
          "source": "MM2024"
        }
      },
      "_key": "!actors.items!VaMhGSEU1kCHtHFC.iV3DKLKD56K4Aq4T"
    },
    {
      "_id": "jvtcWnRLiUwIQAK2",
      "name": "Sopro de Frio (Recarga 5)",
      "type": "feat",
      "img": "icons/svg/aura.svg",
      "system": {
        "description": {
          "value": "<p>Teste de Resistência de Constituição: CD 13, cada criatura em um Cone de 4,5 m. Falha: 18 (4d8) de dano de frio. Sucesso: Metade do dano.</p>",
          "chat": ""
        },
        "activation": {
          "type": "action",
          "value": null,
          "condition": ""
        },
        "uses": {
          "spent": 0,
          "max": "1",
          "recovery": [
            {
              "period": "recharge",
              "type": "recoverAll",
              "formula": "5"
            }
          ]
        },
        "type": {
          "value": "monster",
          "subtype": ""
        },
        "activities": {
          "ZjxjO21VfFSRxlIx": {
            "_id": "ZjxjO21VfFSRxlIx",
            "type": "save",
            "activation": {
              "type": "action",
              "value": null,
              "override": true,
              "condition": ""
            },
            "save": {
              "ability": [
                "con"
              ],
              "dc": {
                "calculation": "",
                "formula": "13"
              }
            },
            "damage": {
              "onSave": "half",
              "parts": []
            }
          }
        }
      },
      "flags": {
        "mm2024": {
          "mechanics": {
            "saveDc": 13,
            "saveAbility": "con"
          },
          "source": "MM2024"
        }
      },
      "_key": "!actors.items!VaMhGSEU1kCHtHFC.jvtcWnRLiUwIQAK2"
    },
    {
      "_id": "rsiIaZQ7SnRwYAKX",
      "name": "Sopro Paralisante",
      "type": "feat",
      "img": "icons/svg/aura.svg",
      "system": {
        "description": {
          "value": "<p>Teste de Resistência de Constituição: CD 13, cada criatura em um Cone de 4,5 m. Primeira Falha: O alvo fica com a condição Incapacitado até o final do próximo turno dele, quando repete o teste. Segunda Falha: O alvo fica com a condição Paralisado e repete o teste ao final de cada turno dele, terminando o efeito em si mesmo com um sucesso. Após 1 minuto, ele tem sucesso automaticamente.</p>",
          "chat": ""
        },
        "activation": {
          "type": "action",
          "value": null,
          "condition": ""
        },
        "uses": {
          "spent": 0,
          "max": "",
          "recovery": []
        },
        "type": {
          "value": "monster",
          "subtype": ""
        },
        "activities": {
          "JgnRzU1czYclfXgJ": {
            "_id": "JgnRzU1czYclfXgJ",
            "type": "save",
            "activation": {
              "type": "action",
              "value": null,
              "override": true,
              "condition": ""
            },
            "save": {
              "ability": [
                "con"
              ],
              "dc": {
                "calculation": "",
                "formula": "13"
              }
            },
            "damage": {
              "onSave": "half",
              "parts": []
            }
          }
        }
      },
      "flags": {
        "mm2024": {
          "mechanics": {
            "saveDc": 13,
            "saveAbility": "con"
          },
          "source": "MM2024"
        }
      },
      "_key": "!actors.items!VaMhGSEU1kCHtHFC.rsiIaZQ7SnRwYAKX"
    }
  ],
  "flags": {
    "mm2024": {
      "nameEn": "Silver Dragon Wyrmling",
      "page": 278,
      "cr": "2",
      "warnings": []
    }
  }
}