{
  "_id": "05aqNTYabfknGhaD",
  "_key": "!actors!05aqNTYabfknGhaD",
  "folder": "1QPcErIwVgACFlzi",
  "name": "Vampire Familiar",
  "type": "npc",
  "img": "modules/mm2024-pt-br/assets/tokens/vampire-familiar.webp",
  "system": {
    "abilities": {
      "str": {
        "value": 17,
        "proficient": 0
      },
      "dex": {
        "value": 16,
        "proficient": 1
      },
      "con": {
        "value": 15,
        "proficient": 0
      },
      "int": {
        "value": 10,
        "proficient": 0
      },
      "wis": {
        "value": 10,
        "proficient": 1
      },
      "cha": {
        "value": 4,
        "proficient": 0
      }
    },
    "attributes": {
      "ac": {
        "calc": "flat",
        "flat": 15,
        "formula": ""
      },
      "hp": {
        "value": 65,
        "max": 65,
        "formula": "10d8 + 20",
        "temp": null,
        "tempmax": null
      },
      "movement": {
        "units": "ft",
        "hover": false,
        "walk": 30,
        "climb": 30
      },
      "senses": {
        "units": "ft",
        "darkvision": 60
      },
      "init": {
        "ability": "dex",
        "bonus": ""
      }
    },
    "details": {
      "type": {
        "value": "humanoid",
        "subtype": "",
        "swarm": "",
        "custom": ""
      },
      "alignment": "Neutro",
      "cr": 3,
      "xp": {
        "value": 700
      },
      "source": {
        "custom": "Monster Manual 2024"
      },
      "biography": {
        "value": ""
      }
    },
    "traits": {
      "size": "med",
      "di": {
        "value": [],
        "custom": "Charmed (except from its vampire master)"
      },
      "dr": {
        "value": [
          "necrotic"
        ],
        "custom": ""
      },
      "dv": {
        "value": [],
        "custom": ""
      },
      "ci": {
        "value": [],
        "custom": ""
      },
      "languages": {
        "value": [],
        "custom": "Common plus one other language"
      }
    },
    "skills": {}
  },
  "prototypeToken": {
    "name": "Vampire Familiar",
    "actorLink": false,
    "sight": {
      "enabled": true
    },
    "texture": {
      "src": "modules/mm2024-pt-br/assets/tokens/vampire-familiar.webp"
    },
    "disposition": -1
  },
  "items": [
    {
      "_id": "n1dbZ9YhJhUkfy9l",
      "name": "Habilidade",
      "type": "feat",
      "img": "icons/svg/aura.svg",
      "system": {
        "description": {
          "value": "<p>• Vampiric Connection. While the familiar and its vampire master are on the same plane of existence, the vampire can communicate with the familiar telepathically, and the vampire can perceive through the familiar's senses.</p>",
          "chat": ""
        },
        "activation": {
          "type": "",
          "value": null
        },
        "uses": {
          "spent": 0,
          "max": "",
          "recovery": []
        },
        "type": {
          "value": "monster",
          "subtype": ""
        },
        "activities": {}
      },
      "flags": {
        "mm2024": {
          "mechanics": {},
          "source": "MM2024"
        }
      },
      "_key": "!actors.items!05aqNTYabfknGhaD.n1dbZ9YhJhUkfy9l"
    },
    {
      "_id": "i3tsWyc37qaQOV8a",
      "name": "Ataque Múltiplo",
      "type": "feat",
      "img": "icons/svg/aura.svg",
      "system": {
        "description": {
          "value": "<p>The familiar makes two Umbral Dag- ger attacks. Umbra/ Dagger. Rolagem de Ataque Corpo a Corpo ou à Distância: +5, alcance 5 ft. or range 20/60 ft. Acerto: 5 (1d4 + 3) Perfurante de dano plus 7 (3d4) Necrótico de dano. If o alvo is reduced to 0 Pontos de Vida by this attack, o alvo becomes Stable but has the Envenenado condition for 1 hour. While it has the Envenenado condition, o alvo has the Paralisado condition.</p>",
          "chat": ""
        },
        "activation": {
          "type": "action",
          "value": null,
          "condition": ""
        },
        "uses": {
          "spent": 0,
          "max": "",
          "recovery": []
        },
        "type": {
          "value": "monster",
          "subtype": ""
        },
        "activities": {
          "5pEu7btZbh7ltQcM": {
            "_id": "5pEu7btZbh7ltQcM",
            "type": "attack",
            "activation": {
              "type": "action",
              "value": null,
              "override": true,
              "condition": ""
            },
            "attack": {
              "ability": "",
              "bonus": "5",
              "flat": true,
              "type": {
                "value": "ranged",
                "classification": "weapon"
              }
            },
            "damage": {
              "includeBase": false,
              "parts": [
                {
                  "number": 1,
                  "denomination": 4,
                  "bonus": "3",
                  "types": [
                    "piercing"
                  ],
                  "custom": {
                    "enabled": false,
                    "formula": ""
                  },
                  "scaling": {
                    "mode": "",
                    "number": 1,
                    "formula": ""
                  }
                }
              ]
            }
          }
        }
      },
      "flags": {
        "mm2024": {
          "mechanics": {
            "toHit": 5,
            "attackType": "ranged",
            "damageFormula": "1d4+3",
            "damageType": "piercing"
          },
          "source": "MM2024"
        }
      },
      "_key": "!actors.items!05aqNTYabfknGhaD.i3tsWyc37qaQOV8a"
    },
    {
      "_id": "hktv13u76Pk9h6mE",
      "name": "Deathless Agility",
      "type": "feat",
      "img": "icons/svg/aura.svg",
      "system": {
        "description": {
          "value": "<p>The familiar takes the Dash or Disen- gage action. MONSTER ENTRIES Most of the book is composed of monster sections that have the following parts after a section's title.</p>",
          "chat": ""
        },
        "activation": {
          "type": "bonus",
          "value": null,
          "condition": ""
        },
        "uses": {
          "spent": 0,
          "max": "",
          "recovery": []
        },
        "type": {
          "value": "monster",
          "subtype": ""
        },
        "activities": {}
      },
      "flags": {
        "mm2024": {
          "mechanics": {},
          "source": "MM2024"
        }
      },
      "_key": "!actors.items!05aqNTYabfknGhaD.hktv13u76Pk9h6mE"
    }
  ],
  "flags": {
    "mm2024": {
      "nameEn": "VAMPIRE FAMILIAR",
      "page": 7,
      "cr": "3",
      "warnings": []
    }
  }
}
